vsngcolabi/__init__.py
vsng_colab-1.2.0.dist-info/METADATA
vsng_colab-1.2.0.dist-info/WHEEL
vsng_colab-1.2.0.dist-info/top_level.txt
vsng_colab-1.2.0.dist-info/RECORD
