Metadata-Version: 2.1
Name: vsng-colab
Version: 1.2.0
Summary: Python Package made by Mhadhbi Issam . 
Home-page: https://gitlab.com/isampypi/vsng-colab
Author: Mhadhbi Issam
Author-email: mhadhbixissam@gmail.com
Classifier: Programming Language :: Python :: 3
Classifier: License :: OSI Approved :: MIT License
Classifier: Operating System :: OS Independent
